simpleweathercli/__init__.py
simpleweathercli/cli.py
simpleweathercli-0.1.3.dist-info/LICENSE
simpleweathercli-0.1.3.dist-info/METADATA
simpleweathercli-0.1.3.dist-info/WHEEL
simpleweathercli-0.1.3.dist-info/entry_points.txt
simpleweathercli-0.1.3.dist-info/top_level.txt
simpleweathercli-0.1.3.dist-info/RECORD
