Metadata-Version: 2.1
Name: simpleweathercli
Version: 0.1.3
Summary: SimpleWeatherCLI is a simple command-line to find weather conditions in a city. It uses current and forecast data provided via API by https://openweathermap.org/. The purpose of this project is to create a simple example of a command-line interfaces using http://docopt.org/ and use Github Actions to build and upload the package to https://pypi.org/.
Home-page: https://github.com/kriogman/weathercli
Author: Javier Gonzalez
Author-email: jgonzalezf@gmail.com
License: MIT
Keywords: weather app simpleweathercli
Platform: UNKNOWN
Classifier: Development Status :: 3 - Alpha
Classifier: License :: OSI Approved :: MIT License
Classifier: Programming Language :: Python :: 3.9
Classifier: Topic :: Text Processing :: Linguistic
Requires-Dist: requests
Requires-Dist: docopt
